deepmusic/__init__.py
deepmusic/composer.py
deepmusic/imgconnector.py
deepmusic/keyboardcell.py
deepmusic/midiconnector.py
deepmusic/model.py
deepmusic/model_old.py
deepmusic/moduleloader.py
deepmusic/modulemanager.py
deepmusic/musicdata.py
deepmusic/songstruct.py
deepmusic/tfutils.py
DeepMusicshot-0.0.1.dist-info/METADATA
DeepMusicshot-0.0.1.dist-info/WHEEL
DeepMusicshot-0.0.1.dist-info/top_level.txt
DeepMusicshot-0.0.1.dist-info/RECORD
