Metadata-Version: 2.1
Name: DeepMusicshot
Version: 0.0.1
Summary: Streaming msic data via neural networks
Author: ZXEcoder
Author-email: <surajjha@gmail.com>
Keywords: python,music,stream,neural networks,sockets
Classifier: Development Status :: 1 - Planning
Classifier: Intended Audience :: Developers
Classifier: Programming Language :: Python :: 3
Classifier: Operating System :: Unix
Classifier: Operating System :: MacOS :: MacOS X
Classifier: Operating System :: Microsoft :: Windows
